ssm/__init__.py
ssm/datastore.py
ssm/interface.py
ssm/main.py
ssm/nframes.py
ssmanager-0.8.11.dist-info/LICENSE.md
ssmanager-0.8.11.dist-info/METADATA
ssmanager-0.8.11.dist-info/WHEEL
ssmanager-0.8.11.dist-info/entry_points.txt
ssmanager-0.8.11.dist-info/top_level.txt
ssmanager-0.8.11.dist-info/RECORD
