Metadata-Version: 2.1
Name: ssmanager
Version: 0.8.11
Summary: A Simple SSH Manager for your terminal written in Python.
Home-page: UNKNOWN
Author: Garrett Jones
Author-email: jonesgc137@gmail.com
License: UNKNOWN
Keywords: ssh,manager,password,networking
Platform: UNKNOWN
Classifier: Programming Language :: Python :: 3
Classifier: Operating System :: Unix
Classifier: Operating System :: MacOS :: MacOS X
Classifier: Operating System :: Microsoft :: Windows
Requires-Python: >=3.0
License-File: LICENSE.md
Requires-Dist: appdirs (>=1.4.4)
Requires-Dist: python-decouple (>=3.6)
Requires-Dist: requests (>=2.25.1)
Requires-Dist: urllib3 (>=1.26.5)
